setup.py
distribution_project/Binomialdistribution.py
distribution_project/Gaussiandistribution.py
distribution_project/Generaldistribution.py
distribution_project/__init__.py
distribution_project.egg-info/PKG-INFO
distribution_project.egg-info/SOURCES.txt
distribution_project.egg-info/dependency_links.txt
distribution_project.egg-info/not-zip-safe
distribution_project.egg-info/top_level.txt